<odoo>
    <data>
        <record id="view_country_state_tree_calendar_csj" model="ir.ui.view">
            <field name="name">res.country.state.tree</field>
            <field name="model">res.country.state</field>
            <field name="inherit_id" ref="base.view_country_state_tree"/>
            <field name="arch" type="xml">
                <xpath expr="//field[@name='country_id']" position="after">
                    <field name="dane_code"/>
                </xpath>
            </field>
        </record>
    </data>
</odoo>
